
{
    "positions":{
        "quantity":15, 
        "pieces":[
                {
                "position":"B_3",
                "name":"white_pawn"
            },
            {
                "position":"G_3",
                "name":"white_pawn"
            },
            {
                "position":"G_4",
                "name":"white_pawn"
            },
            {
                "position":"H_2",
                "name":"white_pawn"
            },
            {
                "position":"D_1",
                "name":"white_knight"
            },
            {
                "position":"D_2",
                "name":"white_knight"
            },
            {
                "position":"D_3",
                "name":"white_rook"
            },
            {
                "position":"G_2",
                "name":"white_bishop"
            },
            {
                "position":"H_1",
                "name":"white_king"
            },
            {
                "position":"B_4",
                "name":"black_pawn"
            },
            {
                "position":"F_7",
                "name":"black_pawn"
            },
            {
                "position":"H_6",
                "name":"black_pawn"
            },
            {
                "position":"E_1",
                "name":"black_rook"
            },
            {
                "position":"F_2",
                "name":"black_queen"
            },
            {
                "position":"G_7",
                "name":"black_king"
            }
        ] 
    }    
}        
